sec_mcp/__init__.py
sec_mcp/cli.py
sec_mcp/config.json
sec_mcp/mcp_server.py
sec_mcp/sec_mcp.py
sec_mcp/start_server.py
sec_mcp/storage.py
sec_mcp/update_blacklist.py
sec_mcp/utility.py
sec_mcp/tests/test_cli.py
sec_mcp/tests/test_sec_mcp.py
sec_mcp/tests/test_storage.py
sec_mcp/tests/test_update_blacklist.py
sec_mcp/tests/test_utility.py
sec_mcp-0.2.7.dist-info/licenses/LICENSE
sec_mcp-0.2.7.dist-info/METADATA
sec_mcp-0.2.7.dist-info/WHEEL
sec_mcp-0.2.7.dist-info/entry_points.txt
sec_mcp-0.2.7.dist-info/top_level.txt
sec_mcp-0.2.7.dist-info/RECORD
