Metadata-Version: 2.4
Name: sec-mcp
Version: 0.2.7
Summary: Python toolkit providing security checks for domains, URLs, IPs, and more.
Author: Montimage
Author-email: contact@montimage.eu
License-Expression: MIT
Project-URL: Homepage, https://github.com/Montimage/sec-mcp
Project-URL: Repository, https://github.com/Montimage/sec-mcp.git
Project-URL: Documentation, https://github.com/Montimage/sec-mcp#readme
Keywords: security,blacklist,mcp,phishing,malware
Classifier: Programming Language :: Python :: 3
Classifier: Programming Language :: Python :: 3.11
Classifier: Topic :: Security
Requires-Python: >=3.11
License-File: LICENSE
Requires-Dist: requests>=2.31.0
Requires-Dist: httpx>=0.25.0
Requires-Dist: click>=8.1.7
Requires-Dist: idna>=3.4
Requires-Dist: mcp[cli]>=0.1.0
Requires-Dist: schedule>=1.2.0
Requires-Dist: tqdm>=4.66.0
Dynamic: author-email
Dynamic: license-file
Dynamic: requires-python
